{
  "items": [
    {
      "slug": "example-slug",
      "aliases": ["alias-1", "alias-2"],
      "name": "示例景点中文名",
      "nameEn": "Example Attraction",
      "district": { "zh": "示例区", "en": "Example District" },
      "rating": 4.5,
      "image": "https://example.com/image.jpg",
      "seo": {
        "title": { "zh": "示例中文标题 | Example", "en": "Example | 示例中文标题" },
        "description": { "zh": "中文 SEO 描述", "en": "English SEO description" }
      },
      "intro": {
        "zh": ["中文介绍段落1", "中文介绍段落2"],
        "en": ["English paragraph 1", "English paragraph 2"]
      },
      "highlights": [
        { "icon": "fas fa-check-circle", "zh": "亮点一", "en": "Highlight One" },
        { "icon": "fas fa-check-circle", "zh": "亮点二", "en": "Highlight Two" }
      ]
    }
  ]
}
